odoo/addons/website_sale_comparison_hide_price/README.rst
odoo/addons/website_sale_comparison_hide_price/__init__.py
odoo/addons/website_sale_comparison_hide_price/__manifest__.py
odoo/addons/website_sale_comparison_hide_price/i18n/es.po
odoo/addons/website_sale_comparison_hide_price/i18n/it.po
odoo/addons/website_sale_comparison_hide_price/i18n/website_sale_comparison_hide_price.pot
odoo/addons/website_sale_comparison_hide_price/readme/CONTRIBUTORS.rst
odoo/addons/website_sale_comparison_hide_price/readme/DESCRIPTION.rst
odoo/addons/website_sale_comparison_hide_price/static/description/icon.png
odoo/addons/website_sale_comparison_hide_price/static/description/index.html
odoo/addons/website_sale_comparison_hide_price/views/website_sale_template.xml
odoo_addon_website_sale_comparison_hide_price-16.0.1.0.0.7.dist-info/METADATA
odoo_addon_website_sale_comparison_hide_price-16.0.1.0.0.7.dist-info/WHEEL
odoo_addon_website_sale_comparison_hide_price-16.0.1.0.0.7.dist-info/top_level.txt
odoo_addon_website_sale_comparison_hide_price-16.0.1.0.0.7.dist-info/RECORD
